[
  {
    "id": 1,
    "start": "00:00:01,000",
    "end": "00:00:05,000",
    "text": "李明在等待小雨的到来，他看了看手表，神情焦急。",
    "emotion": {
      "type": "neutral",
      "description": "NEUTRAL",
      "score": 0.5
    }
  },
  {
    "id": 2,
    "start": "00:00:07,500",
    "end": "00:00:10,500",
    "text": "远处，小雨匆匆跑来，手里拿着一个包。",
    "emotion": {
      "type": "neutral",
      "description": "NEUTRAL",
      "score": 0.5
    }
  },
  {
    "id": 3,
    "start": "00:00:12,000",
    "end": "00:00:16,500",
    "text": "小雨：对不起，我迟到了，路上堵车！",
    "emotion": {
      "type": "neutral",
      "description": "NEUTRAL",
      "score": 0.55
    }
  },
  {
    "id": 4,
    "start": "00:00:18,000",
    "end": "00:00:22,000",
    "text": "李明微笑着摇摇头：没关系，我刚到不久。这是送你的礼物。",
    "emotion": {
      "type": "neutral",
      "description": "NEUTRAL",
      "score": 0.9
    }
  },
  {
    "id": 5,
    "start": "00:00:24,000",
    "end": "00:00:28,000",
    "text": "小雨惊讶地看着礼物盒：哇！这是给我的吗？太感谢了！！！",
    "emotion": {
      "type": "neutral",
      "description": "NEUTRAL",
      "score": 0.9
    }
  },
  {
    "id": 6,
    "start": "00:00:30,000",
    "end": "00:00:35,000",
    "text": "李明：打开看看吧，希望你会喜欢。",
    "emotion": {
      "type": "neutral",
      "description": "NEUTRAL",
      "score": 0.9
    }
  },
  {
    "id": 7,
    "start": "00:00:37,000",
    "end": "00:00:42,000",
    "text": "小雨打开礼物，是一条精美的项链，她的眼睛顿时亮了起来。",
    "emotion": {
      "type": "neutral",
      "description": "NEUTRAL",
      "score": 0.5
    }
  },
  {
    "id": 8,
    "start": "00:00:44,000",
    "end": "00:00:49,000",
    "text": "小雨：这太漂亮了！我真的很喜欢！谢谢你！",
    "emotion": {
      "type": "neutral",
      "description": "NEUTRAL",
      "score": 0.9
    }
  },
  {
    "id": 9,
    "start": "00:00:51,000",
    "end": "00:00:56,000",
    "text": "突然，小雨的手机响了。她看了一眼屏幕，脸色立刻变得苍白。",
    "emotion": {
      "type": "neutral",
      "description": "NEUTRAL",
      "score": 0.5
    }
  },
  {
    "id": 10,
    "start": "00:00:58,000",
    "end": "00:01:04,000",
    "text": "小雨：我妈妈出事了...我必须马上去医院！对不起...",
    "emotion": {
      "type": "neutral",
      "description": "NEUTRAL",
      "score": 0.65
    }
  },
  {
    "id": 11,
    "start": "00:01:06,000",
    "end": "00:01:10,000",
    "text": "李明：别担心，我和你一起去！快走吧！",
    "emotion": {
      "type": "neutral",
      "description": "NEUTRAL",
      "score": 0.6
    }
  },
  {
    "id": 12,
    "start": "00:01:12,000",
    "end": "00:01:18,000",
    "text": "两人迅速离开，李明一直握着小雨的手安慰她。",
    "emotion": {
      "type": "neutral",
      "description": "NEUTRAL",
      "score": 0.5
    }
  },
  {
    "id": 13,
    "start": "00:01:20,000",
    "end": "00:01:26,000",
    "text": "医院走廊上，小雨焦急地等待着，李明轻声安慰她。",
    "emotion": {
      "type": "neutral",
      "description": "NEUTRAL",
      "score": 0.5
    }
  },
  {
    "id": 14,
    "start": "00:01:28,000",
    "end": "00:01:34,000",
    "text": "医生终于走出手术室：手术很成功，没有大碍了。",
    "emotion": {
      "type": "neutral",
      "description": "NEUTRAL",
      "score": 0.5
    }
  },
  {
    "id": 15,
    "start": "00:01:36,000",
    "end": "00:01:42,000",
    "text": "小雨松了一口气，泪水夺眶而出，紧紧抱住了李明。",
    "emotion": {
      "type": "neutral",
      "description": "NEUTRAL",
      "score": 0.5
    }
  }
]